{"the": 1, "i": 2, "and": 3, "a": 4, "to": 5, "b'": 6, "was": 7, "hotel": 8, "in": 9, "at": 10, "we": 11, "for": 12, "chicago": 13, "my": 14, "of": 15, "is": 16, "room": 17, "this": 18, "it": 19, "with": 20, "stayed": 21, "stay": 22, "had": 23, "that": 24, "on": 25, "were": 26, "very": 27, "our": 28, "not": 29, "have": 30, "from": 31, "great": 32, "when": 33, "as": 34, "they": 35, "there": 36, "you": 37, "staff": 38, "be": 39, "are": 40, "but": 41, "one": 42, "rooms": 43, "so": 44, "all": 45, "me": 46, "an": 47, "would": 48, "location": 49, "service": 50, "after": 51, "just": 52, "'": 53, "first": 54, "business": 55, "night": 56, "by": 57, "up": 58, "here": 59, "'t": 60, "nice": 61, "weekend": 62, "nights": 63, "time": 64, "recently": 65, "out": 66, "booked": 67, "got": 68, "husband": 69, "desk": 70, "us": 71, "place": 72, "check": 73, "good": 74, "about": 75, "what": 76, "experience": 77, "like": 78, "trip": 79, "could": 80, "while": 81, "no": 82, "arrived": 83, "get": 84, "bed": 85, "hilton": 86, "hotels": 87, "if": 88, "'s": 89, "front": 90, "wife": 91, "downtown": 92, "will": 93, "been": 94, "two": 95, "only": 96, "really": 97, "did": 98, "has": 99, "staying": 100, "clean": 101, "their": 102, "2": 103, "best": 104, "wonderful": 105, "last": 106, "made": 107, "hotel'": 108, "beautiful": 109, "because": 110, "back": 111, "some": 112, "other": 113, "lobby": 114, "can": 115, "day": 116, "than": 117, "or": 118, "chicago'": 119, "over": 120, "view": 121, "went": 122, "3": 123, "city": 124, "well": 125, "away": 126, "helpful": 127, "say": 128, "family": 129, "also": 130, "never": 131, "which": 132, "more": 133, "looking": 134, "hard": 135, "into": 136, "excellent": 137, "friendly": 138, "everything": 139, "much": 140, "ever": 141, "checked": 142, "bathroom": 143, "reviews": 144, "rock": 145, "water": 146, "even": 147, "reservation": 148, "ambassador": 149, "again": 150, "5": 151, "located": 152, "millennium": 153, "james": 154, "do": 155, "loved": 156, "your": 157, "found": 158, "am": 159, "comfortable": 160, "visit": 161, "suite": 162, "took": 163, "area": 164, "go": 165, "sheraton": 166, "omni": 167, "fairmont": 168, "talbott": 169, "b": 170, "price": 171, "amalfi": 172, "many": 173, "perfect": 174, "enjoyed": 175, "decided": 176, "4": 177, "conrad": 178, "king": 179, "home": 180, "east": 181, "down": 182, "then": 183, "knickerbocker": 184, "few": 185, "house": 186, "sofitel": 187, "right": 188, "michigan": 189, "floor": 190, "next": 191, "way": 192, "disappointed": 193, "called": 194, "luxury": 195, "breakfast": 196, "upon": 197, "find": 198, "allegro": 199, "swissotel": 200, "monaco": 201, "through": 202, "week": 203, "told": 204, "high": 205, "hyatt": 206, "free": 207, "where": 208, "walk": 209, "before": 210, "restaurant": 211, "minutes": 212, "who": 213, "conference": 214, "shopping": 215, "recommend": 216, "going": 217, "its": 218, "most": 219, "three": 220, "intercontinental": 221, "during": 222, "beds": 223, "'ve": 224, "palmer": 225, "wanted": 226, "came": 227, "work": 228, "being": 229, "long": 230, "he": 231, "take": 232, "since": 233, "definitely": 234, "people": 235, "asked": 236, "close": 237, "amazing": 238, "days": 239, "visiting": 240, "she": 241, "wedding": 242, "old": 243, "returned": 244, "travel": 245, "off": 246, "tower": 247, "extremely": 248, "1": 249, "park": 250, "better": 251, "little": 252, "affinia": 253, "food": 254, "star": 255, "regency": 256, "anniversary": 257, "them": 258, "walked": 259, "having": 260, "rate": 261, "quite": 262, "both": 263, "guests": 264, "rude": 265, "any": 266, "how": 267, "gave": 268, "such": 269, "several": 270, "spacious": 271, "small": 272, "always": 273, "felt": 274, "walking": 275, "magnificent": 276, "wait": 277, "towers": 278, "year": 279, "location'": 280, "deal": 281, "website": 282, "bar": 283, "expected": 284, "mile": 285, "hour": 286, "didn": 287, "make": 288, "though": 289, "friends": 290, "size": 291, "absolutely": 292, "nothing": 293, "suites": 294, "door": 295, "fantastic": 296, "around": 297, "left": 298, "want": 299, "need": 300, "thought": 301, "recent": 302, "large": 303, "shower": 304, "once": 305, "new": 306, "customer": 307, "friend": 308, "homewood": 309, "spent": 310, "another": 311, "chose": 312, "too": 313, "looked": 314, "quality": 315, "feel": 316, "vacation": 317, "luxurious": 318, "needed": 319, "every": 320, "pleasant": 321, "heart": 322, "reservations": 323, "able": 324, "four": 325, "second": 326, "amenities": 327, "concierge": 328, "room'": 329, "in'": 330, "clean'": 331, "decor": 332, "modern": 333, "pool": 334, "finally": 335, "times": 336, "love": 337, "see": 338, "highly": 339, "requested": 340, "impressed": 341, "itself": 342, "outside": 343, "know": 344, "sleep": 345, "come": 346, "b'i": 347, "clerk": 348, "everyone": 349, "given": 350, "town": 351, "actually": 352, "her": 353, "worst": 354, "book": 355, "short": 356, "dirty": 357, "sure": 358, "visited": 359, "think": 360, "things": 361, "although": 362, "years": 363, "far": 364, "late": 365, "bit": 366, "money": 367, "huge": 368, "forward": 369, "should": 370, "guest": 371, "easy": 372, "paid": 373, "top": 374, "getaway": 375, "parking": 376, "part": 377, "bad": 378, "ave": 379, "reading": 380, "online": 381, "restaurants": 382, "priceline": 383, "morning": 384, "noise": 385, "building": 386, "almost": 387, "let": 388, "spend": 389, "still": 390, "seemed": 391, "pleased": 392, "review": 393, "10": 394, "within": 395, "used": 396, "air": 397, "daughter": 398, "however'": 399, "expectations": 400, "greeted": 401, "must": 402, "worth": 403, "treated": 404, "use": 405, "call": 406, "favorite": 407, "fun": 408, "pleasure": 409, "expect": 410, "near": 411, "construction": 412, "ready": 413, "distance": 414, "places": 415, "different": 416, "big": 417, "put": 418, "'m": 419, "overall": 420, "moment": 421, "truly": 422, "tv": 423, "arrival": 424, "available": 425, "special": 426, "minute": 427, "pay": 428, "thing": 429, "soon": 430, "look": 431, "reserved": 432, "until": 433, "least": 434, "start": 435, "less": 436, "lake": 437, "fabulous": 438, "end": 439, "double": 440, "6": 441, "person": 442, "offered": 443, "coffee": 444, "views": 445, "kids": 446, "nice'": 447, "couldn": 448, "months": 449, "wasn": 450, "fact": 451, "lot": 452, "read": 453, "name": 454, "navy": 455, "line": 456, "great'": 457, "atmosphere": 458, "'d": 459, "anyone": 460, "each": 461, "couple": 462, "complimentary": 463, "pretty": 464, "excited": 465, "something": 466, "waiting": 467, "all'": 468, "towels": 469, "horrible": 470, "poor": 471, "terrible": 472, "choice": 473, "dinner": 474, "enough": 475, "lovely": 476, "meeting": 477, "friendly'": 478, "getting": 479, "access": 480, "hours": 481, "help": 482, "extra": 483, "night'": 484, "flat": 485, "class": 486, "gorgeous": 487, "try": 488, "don": 489, "30": 490, "seems": 491, "fitness": 492, "set": 493, "walls": 494, "heard": 495, "20": 496, "immediately": 497, "traveling": 498, "decorated": 499, "recommended": 500, "under": 501, "tub": 502, "turned": 503, "happy": 504, "early": 505, "weeks": 506, "attending": 507, "main": 508, "car": 509, "tell": 510, "hear": 511, "'re": 512, "offer": 513, "housekeeping": 514, "15": 515, "enjoy": 516, "didn't": 517, "checking": 518, "met": 519, "simply": 520, "past": 521, "spa": 522, "center": 523, "prices": 524, "romantic": 525, "internet": 526, "average": 527, "traveled": 528, "anything": 529, "might": 530, "upgraded": 531, "awesome": 532, "received": 533, "services": 534, "myself": 535, "relaxing": 536, "expensive": 537, "tired": 538, "full": 539, "neighborhood": 540, "arriving": 541, "summer": 542, "blocks": 543, "done": 544, "live": 545, "convenient": 546, "reception": 547, "knew": 548, "quick": 549, "looks": 550, "art": 551, "hot": 552, "beautifully": 553, "upgrade": 554, "standard": 555, "pier": 556, "phone": 557, "life": 558, "windy": 559, "furniture": 560, "experiences": 561, "attention": 562, "leave": 563, "sheets": 564, "same": 565, "ended": 566, "ok": 567, "expecting": 568, "now": 569, "avenue": 570, "believe": 571, "block": 572, "b'we": 573, "return": 574, "quiet": 575, "said": 576, "00": 577, "company": 578, "group": 579, "warm": 580, "eat": 581, "elegant": 582, "half": 583, "kimpton": 584, "saw": 585, "wine": 586, "b'my": 587, "b'the": 588, "evening": 589, "per": 590, "negative": 591, "river": 592, "convention": 593, "write": 594, "girl": 595, "city'": 596, "previous": 597, "business'": 598, "traveler": 599, "instead": 600, "problem": 601, "often": 602, "also'": 603, "cleaned": 604, "noticed": 605, "toilet": 606, "smoking": 607, "manager": 608, "super": 609, "show": 610, "along": 611, "especially": 612, "returning": 613, "north": 614, "major": 615, "these": 616, "stay'": 617, "attractions": 618, "liked": 619, "july": 620, "wall": 621, "coming": 622, "package": 623, "rather": 624, "spending": 625, "offers": 626, "superb": 627, "tried": 628, "problems": 629, "accommodations": 630, "wrong": 631, "elevator": 632, "his": 633, "give": 634, "overpriced": 635, "fine": 636, "complete": 637, "screen": 638, "treat": 639, "property": 640, "window": 641, "planned": 642, "upscale": 643, "dining": 644, "carpet": 645, "bags": 646, "say'": 647, "month": 648, "originally": 649, "cold": 650, "white": 651, "woke": 652, "smelled": 653, "avoid": 654, "paper": 655, "disappointment": 656, "non": 657, "august": 658, "son": 659, "reasonable": 660, "attend": 661, "professional": 662, "advisor": 663, "birthday": 664, "however": 665, "floor'": 666, "lobby'": 667, "completely": 668, "honeymoon": 669, "saying": 670, "girls": 671, "member": 672, "thru": 673, "local": 674, "particularly": 675, "pillows": 676, "own": 677, "value": 678, "pick": 679, "may": 680, "throughout": 681, "system": 682, "don't": 683, "decent": 684, "entire": 685, "stuff": 686, "arrived'": 687, "directly": 688, "maid": 689, "seen": 690, "stop": 691, "boyfriend": 692, "five": 693, "mini": 694, "included": 695, "whole": 696, "change": 697, "wouldn": 698, "site": 699, "above": 700, "despite": 701, "seem": 702, "charge": 703, "ago": 704, "entering": 705, "booking": 706, "entered": 707, "smaller": 708, "loud": 709, "someone": 710, "pictures": 711, "helped": 712, "wow": 713, "hotwire": 714, "noisy": 715, "airport": 716, "kept": 717, "busy": 718, "boutique": 719, "loop": 720, "cheap": 721, "street": 722, "fan": 723, "historic": 724, "floors": 725, "probably": 726, "usually": 727, "served": 728, "mile'": 729, "ideal": 730, "millenium": 731, "based": 732, "experience'": 733, "without": 734, "classy": 735, "before'": 736, "needs": 737, "september": 738, "already": 739, "totally": 740, "valet": 741, "order": 742, "7": 743, "renovated": 744, "employees": 745, "deluxe": 746, "kitchen": 747, "inside": 748, "club": 749, "corner": 750, "website'": 751, "unfortunately'": 752, "frequent": 753, "weekend'": 754, "swimming": 755, "24": 756, "meet": 757, "prior": 758, "gym": 759, "due": 760, "celebrate": 761, "american": 762, "holiday": 763, "relax": 764, "dog": 765, "gone": 766, "pet": 767, "yet": 768, "counter": 769, "bedroom": 770, "slow": 771, "nearly": 772, "move": 773, "confirmation": 774, "hallway": 775, "else": 776, "first'": 777, "supposed": 778, "cleaning": 779, "advertised": 780, "making": 781, "plan": 782, "children": 783, "points": 784, "cab": 785, "furnished": 786, "provide": 787, "excellent'": 788, "taxi": 789, "chosen": 790, "does": 791, "style": 792, "thanks": 793, "entrance": 794, "sit": 795, "renovation": 796, "others": 797, "areas": 798, "50": 799, "failed": 800, "200": 801, "train": 802, "easily": 803, "stays": 804, "everywhere": 805, "doing": 806, "bring": 807, "choose": 808, "rooms'": 809, "seeing": 810, "level": 811, "plenty": 812, "wifi": 813, "changed": 814, "centrally": 815, "party": 816, "earlier": 817, "charm": 818, "music": 819, "ride": 820, "ask": 821, "yes": 822, "complain": 823, "brief": 824, "placed": 825, "kind": 826, "waited": 827, "flight": 828, "lady": 829, "polite": 830, "incredible": 831, "keep": 832, "trips": 833, "longer": 834, "ordered": 835, "turn": 836, "lower": 837, "started": 838, "process": 839, "request": 840, "ago'": 841, "higher": 842, "experienced": 843, "service'": 844, "either": 845, "across": 846, "smell": 847, "allowed": 848, "point": 849, "perfectly": 850, "well'": 851, "personal": 852, "doors": 853, "establishment": 854, "luggage": 855, "delight": 856, "wish": 857, "key": 858, "shocked": 859, "somewhere": 860, "later": 861, "sent": 862, "issue": 863, "thin": 864, "happened": 865, "light": 866, "unfortunately": 867, "odor": 868, "hopes": 869, "roll": 870, "thoroughly": 871, "difficult": 872, "there'": 873, "wi": 874, "fi": 875, "comfort": 876, "elegance": 877, "again'": 878, "attended": 879, "rest": 880, "saturday": 881, "picked": 882, "gold": 883, "coast": 884, "space": 885, "staff'": 886, "architecture": 887, "downtown'": 888, "twice": 889, "lucky": 890, "features": 891, "including": 892, "living": 893, "bath": 894, "comfortable'": 895, "bathrooms": 896, "interior": 897, "queen": 898, "nearby": 899, "buffet": 900, "lost": 901, "arrive": 902, "meal": 903, "beat": 904, "executive": 905, "drinks": 906, "sights": 907, "south": 908, "wanting": 909, "november": 910, "45": 911, "here'": 912, "pleasantly": 913, "issues": 914, "75": 915, "between": 916, "elegant'": 917, "cost": 918, "uncomfortable": 919, "using": 920, "card": 921, "priceline'": 922, "care": 923, "sister": 924, "december": 925, "central": 926, "motel": 927, "cozy": 928, "rating": 929, "windows": 930, "type": 931, "stunning": 932, "enjoyable": 933, "courteous": 934, "priced": 935, "honestly": 936, "number": 937, "makes": 938, "plus": 939, "watch": 940, "pets": 941, "customers": 942, "satisfied": 943, "surprised": 944, "design": 945, "grand": 946, "lights": 947, "ipod": 948, "lots": 949, "area'": 950, "bedding": 951, "nicer": 952, "trip'": 953, "photos": 954, "dark": 955, "tiny": 956, "behind": 957, "security": 958, "stated": 959, "why": 960, "management": 961, "it'": 962, "pm": 963, "mistake": 964, "bugs": 965, "calls": 966, "unhelpful": 967, "sat": 968, "informed": 969, "exactly": 970, "awful": 971, "touch": 972, "apartment": 973, "certainly": 974, "anniversary'": 975, "notch": 976, "discount": 977, "doorman": 978, "june": 979, "o": 980, "comfy": 981, "girlfriends": 982, "labor": 983, "travelzoo": 984, "older": 985, "tripadvisor": 986, "stocked": 987, "brand": 988, "feeling": 989, "understand": 990, "mid": 991, "october": 992, "'ll": 993, "provides": 994, "drive": 995, "roof": 996, "march": 997, "provided": 998, "list": 999, "finished": 1000, "regular": 1001, "rates": 1002, "it's": 1003, "welcome": 1004, "station": 1005, "l": 1006, "hotels'": 1007, "event": 1008, "spectacular": 1009, "conveniently": 1010, "leisure": 1011, "wonderful'": 1012, "chain": 1013, "side": 1014, "institute": 1015, "small'": 1016, "attentive": 1017, "decision": 1018, "bed'": 1019, "training": 1020, "exceptionally": 1021, "food'": 1022, "pricey": 1023, "afternoon": 1024, "complaint": 1025, "idea": 1026, "via": 1027, "continental": 1028, "corporate": 1029, "decor'": 1030, "25": 1031, "ahead": 1032, "accommodating": 1033, "matter": 1034, "christmas": 1035, "covered": 1036, "variety": 1037, "third": 1038, "amazed": 1039, "overlooking": 1040, "worried": 1041, "somewhat": 1042, "welcoming": 1043, "empty": 1044, "connected": 1045, "web": 1046, "delicious": 1047, "knowledgeable": 1048, "world": 1049, "larger": 1050, "impression": 1051, "stepped": 1052, "reason": 1053, "travelling": 1054, "5th": 1055, "terrace": 1056, "weren": 1057, "day'": 1058, "fit": 1059, "taken": 1060, "paying": 1061, "married": 1062, "working": 1063, "ordinary": 1064, "beyond": 1065, "out'": 1066, "him": 1067, "allow": 1068, "takes": 1069, "fiance": 1070, "taste": 1071, "premium": 1072, "proximity": 1073, "imagine": 1074, "promised": 1075, "television": 1076, "modern'": 1077, "maybe": 1078, "off'": 1079, "giving": 1080, "hilton'": 1081, "future": 1082, "hand": 1083, "frequently": 1084, "guess": 1085, "sized": 1086, "information": 1087, "handle": 1088, "sleeping": 1089, "linens": 1090, "add": 1091, "constant": 1092, "worn": 1093, "hair": 1094, "charged": 1095, "8": 1096, "items": 1097, "maintenance": 1098, "unfriendly": 1099, "assured": 1100, "fail": 1101, "run": 1102, "oh": 1103, "solid": 1104, "smoke": 1105, "running": 1106, "hadn": 1107, "obviously": 1108, "hold": 1109, "cancellation": 1110, "fairly": 1111, "wasn't": 1112, "claims": 1113, "reviews'": 1114, "single": 1115, "com": 1116, "theater": 1117, "february": 1118, "70": 1119, "unhappy": 1120, "showed": 1121, "quiet'": 1122, "rate'": 1123, "stylish": 1124, "true": 1125, "lack": 1126, "prepared": 1127, "possibly": 1128, "smiling": 1129, "said'": 1130, "fitzpatrick": 1131, "planning": 1132, "shopping'": 1133, "dec": 1134, "12": 1135, "delighted": 1136, "lines": 1137, "safe": 1138, "updated": 1139, "break": 1140, "that'": 1141, "outdated": 1142, "tax": 1143, "lovely'": 1144, "eye": 1145, "contact": 1146, "flowers": 1147, "york": 1148, "generally": 1149, "destination": 1150, "spot": 1151, "cannot": 1152, "diamond": 1153, "lounge": 1154, "ta": 1155, "brought": 1156, "sight": 1157, "undergoing": 1158, "notice": 1159, "complaints": 1160, "adequate": 1161, "bathroom'": 1162, "mother": 1163, "towards": 1164, "17": 1165, "headed": 1166, "taking": 1167, "dont": 1168, "sunday": 1169, "restaurants'": 1170, "colors": 1171, "terrific": 1172, "ok'": 1173, "personnel": 1174, "fresh": 1175, "requests": 1176, "overlooked": 1177, "sleeper": 1178, "similar": 1179, "shop": 1180, "mention": 1181, "breathtaking": 1182, "important": 1183, "2007": 1184, "biggest": 1185, "indeed": 1186, "couch": 1187, "open": 1188, "nicest": 1189, "dozen": 1190, "sofa": 1191, "base": 1192, "11": 1193, "closed": 1194, "table": 1195, "appeared": 1196, "chance": 1197, "glad": 1198, "doesn": 1199, "waste": 1200, "selected": 1201, "bellman": 1202, "usual": 1203, "helpful'": 1204, "2nd": 1205, "exceeded": 1206, "haven": 1207, "mentioned": 1208, "w": 1209, "reach": 1210, "detail": 1211, "i've": 1212, "added": 1213, "cancelled": 1214, "concert": 1215, "april": 1216, "happen": 1217, "choices": 1218, "place'": 1219, "couldn't": 1220, "describe": 1221, "forget": 1222, "thank": 1223, "i'm": 1224, "writing": 1225, "appointed": 1226, "vacation'": 1227, "e": 1228, "overall'": 1229, "luxurious'": 1230, "rex": 1231, "realized": 1232, "indoor": 1233, "exceptional": 1234, "color": 1235, "facility": 1236, "plush": 1237, "center'": 1238, "serve": 1239, "positive": 1240, "reservations'": 1241, "designer": 1242, "massage": 1243, "stars": 1244, "email": 1245, "but'": 1246, "pampered": 1247, "stuffy": 1248, "2010": 1249, "incredibly": 1250, "this'": 1251, "step": 1252, "recently'": 1253, "crappy": 1254, "contemporary": 1255, "wireless": 1256, "date": 1257, "accommodate": 1258, "suite'": 1259, "and'": 1260, "carpets": 1261, "assistance": 1262, "job": 1263, "c": 1264, "basically": 1265, "mattress": 1266, "those": 1267, "museums": 1268, "exorbitant": 1269, "hallways": 1270, "ratings": 1271, "receptionist": 1272, "hall": 1273, "send": 1274, "gift": 1275, "sorry": 1276, "apart": 1277, "glowing": 1278, "response": 1279, "guaranteed": 1280, "confirmed": 1281, "worse": 1282, "inn": 1283, "rave": 1284, "plumbing": 1285, "barely": 1286, "control": 1287, "leaving": 1288, "broken": 1289, "seriously": 1290, "warning": 1291, "managers": 1292, "annoying": 1293, "options": 1294, "parents": 1295, "conditioner": 1296, "rated": 1297, "nightmare": 1298, "supper": 1299, "rep": 1300, "workers": 1301, "priced'": 1302, "john": 1303, "affordable": 1304, "east'": 1305, "handy": 1306, "bunch": 1307, "together": 1308, "surrounded": 1309, "marble": 1310, "flew": 1311, "'hare": 1312, "january": 1313, "spacious'": 1314, "cafe": 1315, "word": 1316, "bottom": 1317, "m": 1318, "outstanding": 1319, "sales": 1320, "mess": 1321, "paint": 1322, "disappointing": 1323, "remodeled": 1324, "affina": 1325, "road": 1326, "alone": 1327, "member'": 1328, "history": 1329, "beautiful'": 1330, "blown": 1331, "pier'": 1332, "parked": 1333, "remote": 1334, "spotless": 1335, "bus": 1336, "state": 1337, "3rd": 1338, "charming": 1339, "dinning": 1340, "black": 1341, "updating": 1342, "doubt": 1343, "phenomenal": 1344, "arranged": 1345, "concerned": 1346, "checkout": 1347, "efficient": 1348, "separate": 1349, "attached": 1350, "tourists": 1351, "keeping": 1352, "suggested": 1353, "finding": 1354, "college": 1355, "mom": 1356, "pros": 1357, "hotel's": 1358, "assist": 1359, "relaxed": 1360, "amazingly": 1361, "low": 1362, "dollars": 1363, "except": 1364, "giant": 1365, "renovations": 1366, "el": 1367, "opted": 1368, "2008": 1369, "memorial": 1370, "helpfull": 1371, "miss": 1372, "weekends": 1373, "daily": 1374, "showers": 1375, "leg": 1376, "remarkable": 1377, "fees": 1378, "minor": 1379, "clearly": 1380, "charges": 1381, "ton": 1382, "aug": 1383, "2005": 1384, "extended": 1385, "chi": 1386, "cocktail": 1387, "whether": 1388, "park'": 1389, "european": 1390, "normally": 1391, "staffed": 1392, "summer'": 1393, "scene": 1394, "smooth": 1395, "midway": 1396, "credit": 1397, "magnificant": 1398, "finest": 1399, "locations": 1400, "now'": 1401, "additional": 1402, "boys": 1403, "accessible": 1404, "thursday": 1405, "addition": 1406, "bars": 1407, "shula's": 1408, "elsewhere": 1409, "illinois": 1410, "09": 1411, "reservation'": 1412, "travelled": 1413, "nite": 1414, "cooking": 1415, "dirty'": 1416, "willing": 1417, "transportation": 1418, "didnt": 1419, "suburbs": 1420, "remember": 1421, "cleanest": 1422, "unless": 1423, "june'": 1424, "play": 1425, "time'": 1426, "starwood": 1427, "properties": 1428, "mostly": 1429, "nights'": 1430, "yes'": 1431, "mine": 1432, "cheaper": 1433, "junior": 1434, "reccomend": 1435, "bose": 1436, "property'": 1437, "appetizers": 1438, "recommendations": 1439, "turning": 1440, "health": 1441, "exploring": 1442, "royalty": 1443, "can't": 1444, "lived": 1445, "screen'": 1446, "1st": 1447, "waiter": 1448, "products": 1449, "save": 1450, "surrounding": 1451, "renovated'": 1452, "bottle": 1453, "satisfactory": 1454, "equipment": 1455, "maintained": 1456, "triple": 1457, "suggest": 1458, "b'great": 1459, "delivered": 1460, "aaa": 1461, "excuse": 1462, "aquarium": 1463, "began": 1464, "chic": 1465, "b'this": 1466, "fair": 1467, "ill": 1468, "conditioning": 1469, "unit": 1470, "comes": 1471, "perfect'": 1472, "shuttle": 1473, "conference'": 1474, "figure": 1475, "talking": 1476, "bathrooms'": 1477, "cool'": 1478, "initially": 1479, "express": 1480, "opened": 1481, "42": 1482, "deep": 1483, "feet": 1484, "hour'": 1485, "quick'": 1486, "registration": 1487, "beginning": 1488, "night's": 1489, "machine": 1490, "enjoyment": 1491, "cool": 1492, "golden": 1493, "previously": 1494, "bill": 1495, "fall": 1496, "winter": 1497, "none": 1498, "grant": 1499, "exemplary": 1500, "happier": 1501, "queens": 1502, "nobody": 1503, "b'very": 1504, "pump": 1505, "fiancee": 1506, "immaculate": 1507, "fixed": 1508, "searching": 1509, "blood": 1510, "spring": 1511, "talbot": 1512, "personally": 1513, "bathrobes": 1514, "helping": 1515, "situation": 1516, "laptop": 1517, "cousin": 1518, "worked": 1519, "superior": 1520, "10th": 1521, "filled": 1522, "good'": 1523, "side'": 1524, "flying": 1525, "famous": 1526, "treatment": 1527, "furnishings": 1528, "says": 1529, "eager": 1530, "lavish": 1531, "assisted": 1532, "real": 1533, "man'": 1534, "combination": 1535, "sophistication": 1536, "retro": 1537, "fully": 1538, "respect": 1539, "docking": 1540, "advantage": 1541, "research": 1542, "fell": 1543, "opinion": 1544, "combine": 1545, "fruit": 1546, "opportunity": 1547, "questions": 1548, "price'": 1549, "someplace": 1550, "duty": 1551, "spots": 1552, "visitor": 1553, "days'": 1554, "anywhere": 1555, "accomodations": 1556, "setting": 1557, "difference": 1558, "exquisite": 1559, "hosting": 1560, "enter": 1561, "lets": 1562, "swim": 1563, "gives": 1564, "trendy": 1565, "smile": 1566, "rich": 1567, "known": 1568, "prefer": 1569, "amazing'": 1570, "desired": 1571, "annoyed": 1572, "insisted": 1573, "mind": 1574, "friendliest": 1575, "blanket": 1576, "stuck": 1577, "bag": 1578, "travelers": 1579, "ten": 1580, "downstairs": 1581, "traffic": 1582, "trouble": 1583, "means": 1584, "situated": 1585, "pre": 1586, "pack": 1587, "lengthy": 1588, "kid": 1589, "moved": 1590, "bright": 1591, "severely": 1592, "dingy": 1593, "wacker": 1594, "advance": 1595, "crowds": 1596, "replacement": 1597, "leaked": 1598, "course": 1599, "neighbors": 1600, "elevators": 1601, "complained": 1602, "impossible": 1603, "13": 1604, "required": 1605, "soap": 1606, "dusty": 1607, "gross": 1608, "advance'": 1609, "currently": 1610, "peninsula'": 1611, "dated": 1612, "carpeting": 1613, "eventually": 1614, "public": 1615, "times'": 1616, "inconvenience": 1617, "stand": 1618, "year'": 1619, "classic": 1620, "heating": 1621, "numerous": 1622, "sounded": 1623, "hoping": 1624, "doesnt": 1625, "suitcases": 1626, "cut": 1627, "temperature": 1628, "experiencing": 1629, "interesting": 1630, "understaffed": 1631, "poorly": 1632, "apparently": 1633, "rude'": 1634, "3pm": 1635, "refund": 1636, "worker": 1637, "ice": 1638, "strange": 1639, "rudely": 1640, "asking": 1641, "apologize": 1642, "unpleasant": 1643, "condition": 1644, "general": 1645, "resolve": 1646, "hairs": 1647, "scum": 1648, "attempted": 1649, "phones": 1650, "pool'": 1651, "program": 1652, "fee": 1653, "occasion": 1654, "finally'": 1655, "honor": 1656, "mold": 1657, "repair": 1658, "considered": 1659, "par": 1660, "considering": 1661, "luckily": 1662, "explained": 1663, "colleague": 1664, "firstly'": 1665, "amount": 1666, "forever": 1667, "foot": 1668, "hassle": 1669, "sorely": 1670, "falls": 1671, "unsatisfied": 1672, "foul": 1673, "unfortunate": 1674, "advertises": 1675, "week'": 1676, "acted": 1677, "share": 1678, "do'": 1679, "become": 1680, "activities": 1681, "theme": 1682, "appreciate": 1683, "confirming": 1684, "bigger": 1685, "oh'": 1686, "decorations": 1687, "natural": 1688, "colleagues": 1689, "michigan'": 1690, "orbitz": 1691, "maids": 1692, "heat": 1693, "directed": 1694, "22nd": 1695, "cheerful": 1696, "tim": 1697, "ambiance": 1698, "9": 1699, "29": 1700, "pulled": 1701, "thinking": 1702, "terms": 1703, "entrance'": 1704, "avenue'": 1705, "40th": 1706, "signing": 1707, "virtually": 1708, "delightful": 1709, "unavailable": 1710, "parts": 1711, "25th": 1712, "pillow": 1713, "menu": 1714, "tough": 1715, "fast": 1716, "nervous": 1717, "large'": 1718, "2004": 1719, "nt": 1720, "pleasent": 1721, "refreshing": 1722, "occasions": 1723, "red": 1724, "streets": 1725, "n": 1726, "vs": 1727, "concrete": 1728, "mission": 1729, "groups": 1730, "reasonably": 1731, "100": 1732, "laid": 1733, "closets": 1734, "cities": 1735, "trying": 1736, "direct": 1737, "london": 1738, "airline": 1739, "reflect": 1740, "built": 1741, "ate": 1742, "lockwood": 1743, "breakfasts": 1744, "sense": 1745, "escape": 1746, "resturant": 1747, "social": 1748, "odd": 1749, "nightly": 1750, "members": 1751, "interested": 1752, "secure": 1753, "loop'": 1754, "held": 1755, "funky": 1756, "tasting": 1757, "six": 1758, "space'": 1759, "intercontinental'": 1760, "whatever": 1761, "chocolate": 1762, "opposite": 1763, "tribune": 1764, "exercise": 1765, "workout": 1766, "reasonable'": 1767, "allows": 1768, "otherwise": 1769, "hefty": 1770, "colors'": 1771, "everything'": 1772, "friday": 1773, "shops": 1774, "total": 1775, "panel": 1776, "miracle": 1777, "closer": 1778, "seasons": 1779, "wrote": 1780, "you'": 1781, "passed": 1782, "royal": 1783, "drake": 1784, "fabulous'": 1785, "young": 1786, "bellmen": 1787, "specials": 1788, "sweet": 1789, "alternative": 1790, "65": 1791, "costs": 1792, "painted": 1793, "rain": 1794, "dave": 1795, "judy": 1796, "teenage": 1797, "daughters": 1798, "proved": 1799, "consistently": 1800, "posters": 1801, "beside": 1802, "subway": 1803, "microwave": 1804, "utensils": 1805, "husband'": 1806, "hi'": 1807, "money'": 1808, "works": 1809, "hospitality": 1810, "men": 1811, "ive": 1812, "named": 1813, "greets": 1814, "picture": 1815, "cookies": 1816, "celebrated": 1817, "20th": 1818, "shoes": 1819, "22": 1820, "catered": 1821, "quaint'": 1822, "favourite": 1823, "29th": 1824, "around'": 1825, "finger": 1826, "drink": 1827, "35": 1828, "hd": 1829, "sound": 1830, "suites'": 1831, "eve": 1832, "warmly": 1833, "busy'": 1834, "advanced": 1835, "unbelievably": 1836, "plasma": 1837, "129": 1838, "olds": 1839, "pull": 1840, "obtain": 1841, "decorated'": 1842, "wished": 1843, "please": 1844, "standards": 1845, "brother": 1846, "period": 1847, "may'": 1848, "penthouse": 1849, "goes": 1850, "69": 1851, "normal": 1852, "nbc": 1853, "ran": 1854, "individuals": 1855, "hesitate": 1856, "fast'": 1857, "marriott": 1858, "described": 1859, "women": 1860, "mixed'": 1861, "vouchers": 1862, "onto": 1863, "guy": 1864, "cake": 1865, "7th": 1866, "aria": 1867, "catch": 1868, "atrium": 1869, "return'": 1870, "quickly": 1871, "conrad'": 1872, "maker": 1873, "shower'": 1874, "concern": 1875, "bucks": 1876, "following": 1877, "efficiently": 1878, "heavy": 1879, "freshener": 1880, "beverages": 1881, "nestled": 1882, "completed": 1883, "painless": 1884, "contacted": 1885, "representative": 1886, "wife'": 1887, "plane": 1888, "anticipated": 1889, "managed": 1890, "sun": 1891, "minute'": 1892, "familiar": 1893, "cancellations": 1894, "option": 1895, "types": 1896, "included'": 1897, "posts": 1898, "won": 1899, "awesome'": 1900, "school": 1901, "couples": 1902, "seattle": 1903, "ritz": 1904, "rarely": 1905, "lcd": 1906, "james'": 1907, "designed": 1908, "trade": 1909, "bears": 1910, "breakfast'": 1911, "confirm": 1912, "initial": 1913, "morning'": 1914, "friends'": 1915, "sometimes": 1916, "bartenders": 1917, "appointed'": 1918, "relatively": 1919, "fare": 1920, "french": 1921, "greatest": 1922, "impeccable": 1923, "goldfish": 1924, "170": 1925, "bags'": 1926, "unwind": 1927, "travel'": 1928, "terribly": 1929, "picky": 1930, "hang": 1931, "absolute": 1932, "dream": 1933, "definetly": 1934, "experince": 1935, "scale": 1936, "dealt": 1937, "traveling'": 1938, "stoked": 1939, "team": 1940, "rented": 1941, "yours": 1942, "various": 1943, "luxury'": 1944, "manhattan": 1945, "anybody": 1946, "feels": 1947, "meetings": 1948, "folks": 1949, "tips": 1950, "lot'": 1951, "unique": 1952, "friendliness": 1953, "cam": 1954, "plastic": 1955, "stained": 1956, "common": 1957, "chair": 1958, "afraid": 1959, "t": 1960, "figured": 1961, "ritzy": 1962, "family'": 1963, "opinion'": 1964, "cup": 1965, "month'": 1966, "degrees": 1967, "hidden": 1968, "elegantly": 1969, "attentive'": 1970, "exciting": 1971, "employer": 1972, "selection": 1973, "beauty": 1974, "understatement": 1975, "refreshment": 1976, "cd": 1977, "puts": 1978, "pleasurable": 1979, "million": 1980, "knows": 1981, "movie": 1982, "collection": 1983, "believed": 1984, "suit": 1985, "bank": 1986, "concluded": 1987, "appreciated": 1988, "aveda": 1989, "supplied": 1990, "312": 1991, "wake": 1992, "lunch": 1993, "multiple": 1994, "magnificient": 1995, "agree": 1996, "smoothly": 1997, "entertainment": 1998, "seminar": 1999, "genuinely": 2000, "restroom": 2001, "pleasure'": 2002, "inviting": 2003, "themselves": 2004, "i'": 2005, "better'": 2006, "begin": 2007, "fact'": 2008, "whom": 2009, "glamorous": 2010, "son'": 2011, "accompanied": 2012, "district": 2013, "needed'": 2014, "hoped": 2015, "for'": 2016, "bellhop": 2017, "steaks": 2018, "arrival'": 2019, "impressive": 2020, "knickerbocker'": 2021, "heated": 2022, "youve": 2023, "affordability": 2024, "whenever": 2025, "chairs": 2026, "woman": 2027, "soft": 2028, "lit'": 2029, "children'": 2030, "happily": 2031, "names": 2032, "resist": 2033, "impeccably": 2034, "premiere": 2035, "ceremony": 2036, "wired": 2037, "clerks": 2038, "covers": 2039, "one'": 2040, "breath": 2041, "splurge": 2042, "is'": 2043, "los": 2044, "ourselves": 2045, "housekeepers": 2046, "body": 2047, "located'": 2048, "compelled": 2049, "cleanliness": 2050, "sure'": 2051, "filthy": 2052, "case": 2053, "wood": 2054, "ac": 2055, "nob": 2056, "grapes": 2057, "face": 2058, "alright": 2059, "fly": 2060, "wasnt": 2061, "alot": 2062, "ages": 2063, "seconds": 2064, "carry": 2065, "scenery": 2066, "advise": 2067, "maintained'": 2068, "locate": 2069, "budget": 2070, "steakhouse": 2071, "gets": 2072, "fight": 2073, "lives": 2074, "chef": 2075, "tables": 2076, "champagne": 2077, "glass": 2078, "tourist": 2079, "combined": 2080, "tranquility": 2081, "yoga": 2082, "'luxury": 2083, "sleek": 2084, "museum": 2085, "exudes": 2086, "departure": 2087, "search": 2088, "party'": 2089, "approached": 2090, "desk'": 2091, "overlook": 2092, "beautifull": 2093, "frank": 2094, "receiving": 2095, "assistant": 2096, "forgot": 2097, "purpose": 2098, "replaced": 2099, "hole": 2100, "chipped": 2101, "nasty": 2102, "banging": 2103, "monaco'": 2104, "alley": 2105, "starts": 2106, "30am": 2107, "400": 2108, "girlfriend": 2109, "sitting": 2110, "wallpaper": 2111, "peeling": 2112, "hi": 2113, "ugly": 2114, "dock": 2115, "slamming": 2116, "against": 2117, "smokers": 2118, "country": 2119, "walls'": 2120, "purchased": 2121, "ours": 2122, "registered": 2123, "consecutive": 2124, "inadequate": 2125, "14": 2126, "13th": 2127, "800": 2128, "written": 2129, "policy'": 2130, "register": 2131, "overnight": 2132, "falling": 2133, "basis": 2134, "standing": 2135, "hospital": 2136, "world'": 2137, "resembled": 2138, "wide": 2139, "clark": 2140, "reply": 2141, "bothered": 2142, "answer": 2143, "emails": 2144, "downhill": 2145, "ave'": 2146, "truth": 2147, "california": 2148, "re": 2149, "chairs'": 2150, "overrated": 2151, "30pm": 2152, "unacceptable": 2153, "overbooked": 2154, "ensure": 2155, "ins": 2156, "sheek": 2157, "isn": 2158, "toliet": 2159, "aren": 2160, "conferences": 2161, "2011": 2162, "beer": 2163, "bottles'": 2164, "though'": 2165, "industry": 2166, "slightly": 2167, "incident": 2168, "anthony": 2169, "letter": 2170, "stolen": 2171, "character": 2172, "very'": 2173, "thin'": 2174, "card'": 2175, "conversations": 2176, "wedding'": 2177, "anyway'": 2178, "fixtures": 2179, "clogged": 2180, "illinois'": 2181, "peaceful": 2182, "drain": 2183, "operating": 2184, "note": 2185, "happening": 2186, "illusion": 2187, "enough'": 2188, "'view": 2189, "unable": 2190, "weather": 2191, "celebrating": 2192, "notified": 2193, "ridiculous": 2194, "preferred": 2195, "strong": 2196, "lacking": 2197, "checkin": 2198, "adult": 2199, "below": 2200, "contrary": 2201, "actual": 2202, "regarding": 2203, "voicemails": 2204, "name'": 2205, "bell": 2206, "thier": 2207, "bites": 2208, "hell": 2209, "hesitated": 2210, "gentleman": 2211, "mail": 2212, "me'": 2213, "limited": 2214, "swissotel'": 2215, "min": 2216, "mins": 2217, "fashion": 2218, "messed": 2219, "tickets": 2220, "office": 2221, "agent": 2222, "spoke": 2223, "watched": 2224, "disgusted": 2225, "sign": 2226, "hallways'": 2227, "bolted": 2228, "flush": 2229, "fix": 2230, "often'": 2231, "constantly": 2232, "parties": 2233, "filed": 2234, "man": 2235, "supposedly": 2236, "fails": 2237, "policy": 2238, "charging": 2239, "self": 2240, "boy": 2241, "select": 2242, "disapointed": 2243, "reluctantly": 2244, "agreed": 2245, "accomodating": 2246, "strike": 2247, "incompetent": 2248, "luck": 2249, "le": 2250, "toiletries": 2251, "rooftop": 2252, "meridian": 2253, "cheap'": 2254, "anytime": 2255, "desirable": 2256, "aspires": 2257, "cups": 2258, "whichworked": 2259, "wondeful": 2260, "holder'": 2261, "miserably": 2262, "impressions": 2263, "indicated": 2264, "building'": 2265, "dust": 2266, "cons": 2267, "dangerous": 2268, "spread": 2269, "sympathy": 2270, "cigarette": 2271, "disappointment'": 2272, "meals": 2273, "computer": 2274, "baby": 2275, "array": 2276, "complaining": 2277, "serviced": 2278, "ladies": 2279, "dried": 2280, "enthusiastic": 2281, "monoco": 2282, "elsewhere'": 2283, "host": 2284, "stopped": 2285, "6'": 2286, "appear": 2287, "hyped": 2288, "isnt": 2289, "blankets": 2290, "fun'": 2291, "brick": 2292, "match": 2293, "bathtub": 2294, "compensate": 2295, "haven't": 2296, "expensive'": 2297, "caters": 2298, "portrayed": 2299, "playing": 2300, "doll": 2301, "classical": 2302, "hate": 2303, "images": 2304, "alludes": 2305, "mediocre": 2306, "disaster": 2307, "dissappointed": 2308, "nina": 2309, "erin": 2310, "sharp": 2311, "tip": 2312, "reasons": 2313, "hearing": 2314, "needless": 2315, "jacuzzi": 2316, "properly": 2317, "cart": 2318, "debris": 2319, "advertising": 2320, "private": 2321, "seemingly": 2322, "nor": 2323, "fool": 2324, "approched": 2325, "settled": 2326, "sounds": 2327, "unimpressed": 2328, "misfortune": 2329, "bothering": 2330, "boasts": 2331, "surprise": 2332, "crowded": 2333, "associate": 2334, "atrocious": 2335, "neighbor's": 2336, "lackluster": 2337, "dissatisfied": 2338, "packed": 2339, "forth": 2340, "tenth": 2341, "starters'": 2342, "fancy": 2343, "appalled": 2344, "vending": 2345, "cheese": 2346, "twelveth": 2347, "ones": 2348, "appears": 2349, "guessed": 2350, "theme'": 2351, "23rd": 2352, "sixteen": 2353, "enhanced": 2354, "entwistle": 2355, "fathers": 2356, "accomplish": 2357, "lore": 2358, "midwest": 2359, "remotely": 2360, "travellodge": 2361, "breeze'": 2362, "b'a": 2363, "limes": 2364, "punch": 2365, "bowl": 2366, "extradionary": 2367, "interest": 2368, "dancing": 2369, "courtesy": 2370, "particularily": 2371, "sweetie": 2372, "lures": 2373, "guise": 2374, "china": 2375, "grill'": 2376, "tag": 2377, "smaller'": 2378, "intense'": 2379, "cozy'": 2380, "27th'": 2381, "courtiest": 2382, "attractive": 2383, "sinks": 2384, "stephanie": 2385, "basil": 2386, "lift'": 2387, "putting": 2388, "mixed": 2389, "concierge'": 2390, "glossy": 2391, "sexy'": 2392, "heading": 2393, "quaint": 2394, "romantic'": 2395, "frigid": 2396, "newsletter": 2397, "beware": 2398, "48": 2399, "start'": 2400, "grandeur": 2401, "shining'": 2402, "frankly'": 2403, "facade": 2404, "remain": 2405, "incomplete": 2406, "wet": 2407, "stickers": 2408, "gracious": 2409, "greeting": 2410, "pantry": 2411, "refrigerator": 2412, "ammenities": 2413, "need'": 2414, "courteous'": 2415, "tidy'": 2416, "shortly": 2417, "tuesday'": 2418, "impact": 2419, "peoples": 2420, "split": 2421, "aspects": 2422, "p": 2423, "recreation": 2424, "weren't": 2425, "driving": 2426, "travelzoo'": 2427, "draught": 2428, "stella": 2429, "guinness": 2430, "ae": 2431, "generation": 2432, "grandma'": 2433, "station'": 2434, "viewing": 2435, "dearborn": 2436, "cafe'": 2437, "jungle": 2438, "accomplished": 2439, "subway'": 2440, "facet": 2441, "mariott": 2442, "shared": 2443, "default": 2444, "grey": 2445, "vibe": 2446, "cheesy": 2447, "intact'": 2448, "forewarned": 2449, "condo": 2450, "inexpensive": 2451, "eaten": 2452, "residential": 2453, "ranges": 2454, "bargain": 2455, "timely": 2456, "abd": 2457, "toothbrush": 2458, "toothpaste": 2459, "thechina": 2460, "grill": 2461, "apri": 2462, "round'": 2463, "recognizes": 2464, "sets": 2465, "tone": 2466, "terrific'": 2467, "noted'": 2468, "seasons'": 2469, "gem": 2470, "hectic": 2471, "student": 2472, "pastries'": 2473, "spotlessly": 2474, "tiny'": 2475, "virgin": 2476, "atlantic": 2477, "flights": 2478, "reassured": 2479, "arrrival": 2480, "refurbished": 2481, "gourmet": 2482, "disappoint": 2483, "mornings": 2484, "supervising": 2485, "doormen": 2486, "puppy": 2487, "bargin": 2488, "overly": 2489, "redone": 2490, "lasalle": 2491, "cadillac": 2492, "italian": 2493, "kimptons": 2494, "designer'": 2495, "60": 2496, "centerally": 2497, "steep'": 2498, "excursion": 2499, "redeemed": 2500, "reward": 2501, "minus": 2502, "robes": 2503, "cancelling": 2504, "interview": 2505, "march'": 2506, "december'": 2507, "guys": 2508, "rottweiler": 2509, "accommodation": 2510, "position'": 2511, "31": 2512, "cconference": 2513, "inconveniences": 2514, "breathtaking'": 2515, "plus'": 2516, "blue": 2517, "expedia": 2518, "excutive": 2519, "programs": 2520, "sterile": 2521, "pedestrian": 2522, "metro": 2523, "floors'": 2524, "defintely": 2525, "importantly": 2526, "properties'": 2527, "apprehensive": 2528, "late'": 2529, "became": 2530, "130": 2531, "theatre": 2532, "ic": 2533, "26th": 2534, "werent": 2535, "starbucks": 2536, "hit": 2537, "tremendous'": 2538, "anticipation": 2539, "motivate": 2540, "grab": 2541, "fruit'": 2542, "question'": 2543, "lion": 2544, "moterate": 2545, "gratis": 2546, "'el": 2547, "leaves": 2548, "geared": 2549, "toward": 2550, "crowd": 2551, "january'": 2552, "bachorette": 2553, "knowledge": 2554, "prompt": 2555, "equipped": 2556, "lg": 2557, "zest": 2558, "tucked": 2559, "west": 2560, "wrigley": 2561, "surpassed": 2562, "hotwire'": 2563, "complaints'": 2564, "mag": 2565, "soldier": 2566, "stadium": 2567, "insitiute": 2568, "basic": 2569, "b'well": 2570, "lacks": 2571, "slated": 2572, "'taste": 2573, "4th": 2574, "cocktails": 2575, "51": 2576, "watching": 2577, "swank": 2578, "upgrades": 2579, "bookings": 2580, "ich": 2581, "2006": 2582, "perplexed": 2583, "expect'": 2584, "150": 2585, "orange": 2586, "homeless": 2587, "panhandlers": 2588, "gawdy": 2589, "lollopalooza": 2590, "festival": 2591, "jaymes": 2592, "ballard'": 2593, "landed": 2594, "80": 2595, "41st": 2596, "unbelieveable": 2597, "42nd": 2598, "interfaced": 2599, "extras": 2600, "etc": 2601, "skills": 2602, "surprise'": 2603, "rib": 2604, "steak": 2605, "bartender'": 2606, "granted": 2607, "timey": 2608, "cheesecake": 2609, "factory": 2610, "bloomingdales'": 2611, "foods": 2612, "couldn'": 2613, "chechecked": 2614, "minuses": 2615, "rehabbed": 2616, "plusses": 2617, "wand'": 2618, "cora": 2619, "martini": 2620, "julie": 2621, "lake'": 2622, "july'": 2623, "attractive'": 2624, "skyscraper": 2625, "size'": 2626, "receptions": 2627, "caught": 2628, "thunderstorm'": 2629, "uk": 2630, "pl": 2631, "8th": 2632, "lose'": 2633, "particular": 2634, "trolley": 2635, "solo": 2636, "wardrobe": 2637, "oven": 2638, "nites'": 2639, "texas": 2640, "bottles": 2641, "touches": 2642, "extra'": 2643, "desks": 2644, "open'": 2645, "fox": 2646, "obel'": 2647, "dinners": 2648, "weeknights": 2649, "granddaughters": 2650, "grandma": 2651, "grandaughter": 2652, "outing": 2653, "hancock": 2654, "cleveland": 2655, "valets": 2656, "shoved": 2657, "blast": 2658, "sorts": 2659, "nap": 2660, "die": 2661, "stranded": 2662, "canceled'": 2663, "swisshotel": 2664, "connie": 2665, "shift": 2666, "remembers": 2667, "commented": 2668, "definately": 2669, "3114": 2670, "3115": 2671, "adjoining": 2672, "plate": 2673, "treats": 2674, "walked'": 2675, "gizillion": 2676, "cruise": 2677, "odyssey": 2678, "wearing": 2679, "heels": 2680, "blisters": 2681, "perhaps": 2682, "checkout'": 2683, "88": 2684, "unbelievable": 2685, "oversized'": 2686, "cab'": 2687, "wicked": 2688, "sheratons": 2689, "santa": 2690, "barbara": 2691, "lift": 2692, "palm": 2693, "luckier": 2694, "scared": 2695, "fleabag": 2696, "palace'": 2697, "nieces": 2698, "1519": 2699, "numbered": 2700, "speaker": 2701, "lineds": 2702, "pacage": 2703, "superb'": 2704, "tastefully": 2705, "electronics": 2706, "soaking": 2707, "stall": 2708, "everytime": 2709, "by'": 2710, "bridgestone": 2711, "firestone": 2712, "conventions": 2713, "evidently": 2714, "popular": 2715, "indoors'": 2716, "thanksgiving": 2717, "av": 2718, "damn": 2719, "faint": 2720, "praise": 2721, "screens'": 2722, "55": 2723, "hesitation": 2724, "cards": 2725, "preferential": 2726, "immediate": 2727, "seating": 2728, "joining": 2729, "presidents": 2730, "club'": 2731, "93": 2732, "inc": 2733, "swims": 2734, "band": 2735, "middle": 2736, "year's": 2737, "deals": 2738, "yr": 2739, "newly": 2740, "9th": 2741, "hill": 2742, "eric": 2743, "ordering": 2744, "ports": 2745, "chop": 2746, "shape": 2747, "pristine": 2748, "spur": 2749, "selfpark": 2750, "buckwheat": 2751, "pan": 2752, "cakes": 2753, "egg": 2754, "benedict": 2755, "stunned": 2756, "oddly": 2757, "shaped": 2758, "purifier": 2759, "silently": 2760, "vacationed": 2761, "2009": 2762, "friday'": 2763, "122": 2764, "noted": 2765, "professional'": 2766, "televison": 2767, "bedside": 2768, "treadmills": 2769, "elipitical": 2770, "steppers'": 2771, "river'": 2772, "insanely": 2773, "bf": 2774, "nightspots": 2775, "upscale'": 2776, "coleman": 2777, "sold": 2778, "personality": 2779, "compliments": 2780, "06": 2781, "04": 2782, "05'": 2783, "173": 2784, "steal": 2785, "44in": 2786, "stereo'": 2787, "restaurant'": 2788, "b'stayed": 2789, "largest": 2790, "movies": 2791, "waits": 2792, "shed": 2793, "field": 2794, "musium": 2795, "remains": 2796, "tied": 2797, "umbrella": 2798, "soaked": 2799, "reunion": 2800, "feeling'": 2801, "coolest": 2802, "com'": 2803, "exhibit": 2804, "bent": 2805, "backwards": 2806, "anything'": 2807, "pronounced": 2808, "correctly'": 2809, "huge'": 2810, "scent": 2811, "signed": 2812, "loyalty": 2813, "program'": 2814, "beaten": 2815, "path": 2816, "operate": 2817, "disinterested": 2818, "procedure": 2819, "manchester": 2820, "juice": 2821, "grim": 2822, "sunbeds": 2823, "cheering": 2824, "pleasing'": 2825, "delivers": 2826, "fronts'": 2827, "catching": 2828, "dear": 2829, "rituals": 2830, "10pm": 2831, "atlanta": 2832, "lieu": 2833, "taxis": 2834, "stores'": 2835, "tvs'": 2836, "thirty": 2837, "dispite": 2838, "saying'": 2839, "shabby": 2840, "gratus": 2841, "penninsula": 2842, "skyauction": 2843, "bid": 2844, "203": 2845, "aside'": 2846, "fling": 2847, "tops": 2848, "travellers": 2849, "goldfish'": 2850, "dana": 2851, "secured": 2852, "16thz": 2853, "suitcase": 2854, "happens": 2855, "extrodinary": 2856, "usd": 2857, "exists": 2858, "restuarant": 2859, "printed": 2860, "boarding": 2861, "passes": 2862, "frquently'": 2863, "thoughtfully": 2864, "lighting'": 2865, "faboulous": 2866, "linen'": 2867, "hyatt'": 2868, "deliberation": 2869, "rush": 2870, "st": 2871, "feel'": 2872, "feb": 2873, "27": 2874, "sears": 2875, "joint": 2876, "memorable": 2877, "striking": 2878, "wave": 2879, "at'": 2880, "regularly": 2881, "marathon": 2882, "219": 2883, "positve": 2884, "1112'": 2885, "149": 2886, "was'": 2887, "beds'": 2888, "fault": 2889, "ranked": 2890, "as'": 2891, "nov": 2892, "kitty": 2893, "'shea": 2894, "feather": 2895, "feathers": 2896, "crabtree": 2897, "evelyn": 2898, "shampoo'": 2899, "180": 2900, "skiing": 2901, "easter": 2902, "islands": 2903, "wonderland'": 2904, "serving": 2905, "la": 2906, "carte": 2907, "twist": 2908, "dinner'": 2909, "indicates": 2910, "bedrooms": 2911, "blues": 2912, "fans'": 2913, "town'": 2914, "recognize": 2915, "sylvia": 2916, "rollins'": 2917, "october'": 2918, "seats": 2919, "el'": 2920, "trendy'": 2921, "significant": 2922, "impecable'": 2923, "museums'": 2924, "spoil": 2925, "goldish": 2926, "oliver": 2927, "welcoming'": 2928, "30th": 2929, "tells": 2930, "liberty": 2931, "customizing": 2932, "profile": 2933, "shows": 2934, "careful": 2935, "providing": 2936, "weeknd": 2937, "husbands": 2938, "nicely": 2939, "funny": 2940, "sports": 2941, "fantastic'": 2942, "amusement": 2943, "spaffina": 2944, "pampering": 2945, "perfection": 2946, "stroll": 2947, "mary": 2948, "shampoo": 2949, "personable": 2950, "mundane": 2951, "pleasureable": 2952, "spotless'": 2953, "rose": 2954, "pedals": 2955, "honey": 2956, "moon": 2957, "coordinate": 2958, "organized": 2959, "were'": 2960, "g": 2961, "suckish": 2962, "evan": 2963, "molded": 2964, "sandwhich": 2965, "strives": 2966, "hello": 2967, "current": 2968, "hbo": 2969, "enormous": 2970, "wooden": 2971, "lamp": 2972, "modem": 2973, "workstation": 2974, "finishing": 2975, "lastly": 2976, "slept": 2977, "bay": 2978, "finds": 2979, "equal": 2980, "memorabilia": 2981, "talented": 2982, "artists": 2983, "singers'": 2984, "speed": 2985, "flawlessly": 2986, "luxuriously": 2987, "green": 2988, "consulting": 2989, "firm": 2990, "environmental": 2991, "credentials": 2992, "dovetailed": 2993, "guilt": 2994, "stumbled": 2995, "romance": 2996, "enjoying": 2997, "street'": 2998, "solace": 2999, "invoting": 3000, "rooom": 3001, "ample": 3002, "stuff'": 3003, "expectations'": 3004, "positives": 3005, "bets": 3006, "neat'": 3007, "visit'": 3008, "traits": 3009, "decide": 3010, "unique'": 3011, "greet": 3012, "relatives": 3013, "emphasized": 3014, "environmentally": 3015, "lengths": 3016, "guests'": 3017, "arizona'": 3018, "b'pleasant": 3019, "linnens": 3020, "bedbug": 3021, "german": 3022, "shepard": 3023, "pardon": 3024, "pun": 3025, "laminated": 3026, "snack": 3027, "clients": 3028, "discuss": 3029, "naturally'": 3030, "expected'": 3031, "transcends": 3032, "embraces": 3033, "obligatory": 3034, "commute": 3035, "coffeemaker": 3036, "tea": 3037, "internet'": 3038, "treasure": 3039, "sky": 3040, "scraping": 3041, "steel": 3042, "epicenter": 3043, "inter": 3044, "existence": 3045, "b'amalifa": 3046, "buisness": 3047, "vacationing'": 3048, "christening": 3049, "possible": 3050, "series": 3051, "faces": 3052, "employed": 3053, "escorted": 3054, "dripping": 3055, "bar'": 3056, "throwback": 3057, "era": 3058, "kinzie": 3059, "st'": 3060, "matches": 3061, "concept": 3062, "selections": 3063, "house'": 3064, "welcomed": 3065, "highest": 3066, "recommendation": 3067, "glamour": 3068, "moderately": 3069, "luxuriance": 3070, "forgotten": 3071, "mentioning": 3072, "clerk'": 3073, "rare": 3074, "life'": 3075, "utmost": 3076, "skyscrapers": 3077, "dumbs": 3078, "concourse": 3079, "straight": 3080, "gentlemen": 3081, "cuisine": 3082, "options'": 3083, "b'an": 3084, "stations": 3085, "borrow": 3086, "understated": 3087, "minimalist": 3088, "resonably": 3089, "breaking": 3090, "aka'": 3091, "seven": 3092, "visited'": 3093, "incomparable": 3094, "individualized": 3095, "receive": 3096, "sophisticated": 3097, "senses": 3098, "availability": 3099, "yogurt": 3100, "descent'": 3101, "vip": 3102, "hire": 3103, "dvd": 3104, "microfiber": 3105, "robe": 3106, "slippers": 3107, "you're": 3108, "recommending": 3109, "complimentartry": 3110, "extravagant'": 3111, "admit'": 3112, "considerate'": 3113, "dreading": 3114, "play'": 3115, "proceeded": 3116, "infamous": 3117, "37": 3118, "unpacked": 3119, "hooking": 3120, "omelet": 3121, "nevertheless": 3122, "factors": 3123, "swept": 3124, "pleased'": 3125, "associates": 3126, "technological": 3127, "amenities'": 3128, "sisters": 3129, "attracted": 3130, "finance": 3131, "portions": 3132, "snagged": 3133, "theatre'": 3134, "holidays": 3135, "ramada": 3136, "casey": 3137, "skinner'": 3138, "between'": 3139, "decked": 3140, "luxuries": 3141, "of'": 3142, "abundant'": 3143, "plans": 3144, "theater'": 3145, "hlton": 3146, "flawless": 3147, "nine": 3148, "styles": 3149, "everyones": 3150, "presidential": 3151, "palms'": 3152, "b'elegant": 3153, "modernized": 3154, "separated": 3155, "renting": 3156, "prepare": 3157, "wished'": 3158, "scenic": 3159, "b'when": 3160, "catches": 3161, "tasteful": 3162, "benefits": 3163, "waking": 3164, "bloomingdales": 3165, "plesant": 3166, "decorum": 3167, "recomend": 3168, "heavenly": 3169, "concern'": 3170, "cent": 3171, "b'from": 3172, "overindulgent": 3173, "invite": 3174, "skyline": 3175, "i'll": 3176, "packers": 3177, "monday": 3178, "game": 3179, "rocked": 3180, "lifetime'": 3181, "definitly": 3182, "clientel": 3183, "had'": 3184, "simple": 3185, "bonuses": 3186, "alcoholic": 3187, "meticulously": 3188, "oozing": 3189, "fashioned": 3190, "layouts": 3191, "equipted": 3192, "'second": 3193, "wind": 3194, "unfamiliar": 3195, "solely": 3196, "hungry": 3197, "replenished": 3198, "restful": 3199, "kudos": 3200, "b'stays": 3201, "software": 3202, "marketing": 3203, "firm'": 3204, "complement": 3205, "grabbed": 3206, "rendered": 3207, "tasted'": 3208, "stays'": 3209, "refered": 3210, "utilized": 3211, "package'": 3212, "typical": 3213, "attractions'": 3214, "delious": 3215, "multitude": 3216, "evident": 3217, "glamourous": 3218, "diverse": 3219, "culturally": 3220, "touristy": 3221, "discriminating": 3222, "refined": 3223, "fireplace'": 3224, "travels": 3225, "relaxation": 3226, "fluffy": 3227, "valuables": 3228, "arm": 3229, "authentic": 3230, "'excursion": 3231, "brightly": 3232, "bagpacks": 3233, "remembered": 3234, "utterly": 3235, "conveniences": 3236, "inch": 3237, "hits": 3238, "guestroom": 3239, "packege": 3240, "proficient'": 3241, "graduation": 3242, "sudden": 3243, "driver": 3244, "nearest": 3245, "reams": 3246, "adorned": 3247, "connections": 3248, "hands": 3249, "down'": 3250, "rich'": 3251, "upto": 3252, "def": 3253, "classy'": 3254, "penny": 3255, "tones": 3256, "soothe": 3257, "eyes": 3258, "myspa": 3259, "stiff": 3260, "softness": 3261, "whisked": 3262, "slumber": 3263, "designed'": 3264, "justice": 3265, "venue": 3266, "luxuary'": 3267, "chicago's": 3268, "desire": 3269, "15th": 3270, "pamper": 3271, "worry": 3272, "likes": 3273, "souvenirs": 3274, "him'": 3275, "oppertunity": 3276, "rough": 3277, "angeles": 3278, "graduated": 3279, "join": 3280, "perfecty": 3281, "aesthetics'": 3282, "heaven": 3283, "gates'": 3284, "comfortal": 3285, "tech": 3286, "relax'": 3287, "encountered": 3288, "confad": 3289, "creepy": 3290, "employe": 3291, "dashed": 3292, "that's": 3293, "beauti": 3294, "polished": 3295, "heater": 3296, "ting": 3297, "velveteen": 3298, "paradise": 3299, "68": 3300, "confrotable": 3301, "leather": 3302, "stone": 3303, "uncontentious": 3304, "drowning": 3305, "cause": 3306, "wont": 3307, "olympic": 3308, "beach": 3309, "swimmers": 3310, "florist'": 3311, "tripped": 3312, "socialize": 3313, "distance'": 3314, "crim": 3315, "homey": 3316, "televisions": 3317, "garage": 3318, "unlimited": 3319, "priviledges": 3320, "penalty": 3321, "castle": 3322, "receptionists": 3323, "shape'": 3324, "pda": 3325, "kiosk": 3326, "hypo": 3327, "allergenic": 3328, "purification": 3329, "systems": 3330, "gym'": 3331, "left'": 3332, "plan'": 3333, "amy": 3334, "angelas'": 3335, "upmost": 3336, "tie": 3337, "porter": 3338, "allergy": 3339, "go'": 3340, "tight": 3341, "stetson": 3342, "thumbs": 3343, "celebration": 3344, "suggestions": 3345, "eat'": 3346, "want'": 3347, "soaps": 3348, "confident": 3349, "success": 3350, "desserts": 3351, "pastry": 3352, "baked": 3353, "fountain": 3354, "terry": 3355, "cloth": 3356, "doubts": 3357, "places'": 3358, "heartedly": 3359, "manner": 3360, "creates": 3361, "streamlined'": 3362, "b'beautiful": 3363, "b'excellent": 3364, "accesible": 3365, "essentials": 3366, "always'": 3367, "only'": 3368, "preface": 3369, "largely": 3370, "districts": 3371, "mainly": 3372, "ventured": 3373, "liked'": 3374, "comfort'": 3375, "cousins": 3376, "stunning'": 3377, "blooming": 3378, "historical": 3379, "traveler'": 3380, "musical'": 3381, "pricey'": 3382, "bit'": 3383, "delux": 3384, "poised'": 3385, "colleges": 3386, "surround": 3387, "fortune": 3388, "lodge": 3389, "luxirious": 3390, "cultural": 3391, "definetely": 3392, "reccommend": 3393, "unexpected": 3394, "referred": 3395, "crisp'": 3396, "towns": 3397, "spots'": 3398, "centralized": 3399, "grounds": 3400, "we'll": 3401, "we're": 3402, "practically": 3403, "accessories": 3404, "definition": 3405, "''": 3406, "conduct": 3407, "welcomes": 3408, "followed": 3409, "uber": 3410, "satayed": 3411, "less'": 3412, "willingly": 3413, "thankfully": 3414, "scheduling": 3415, "surprised'": 3416, "comment'": 3417, "immaculately": 3418, "resources": 3419, "ribs": 3420, "youre": 3421, "mood": 3422, "unwind'": 3423, "action'": 3424, "hustle": 3425, "bustle": 3426, "ocean": 3427, "eating": 3428, "wonderfull": 3429, "adventurer": 3430, "paul": 3431, "entice": 3432, "visitors": 3433, "passes'": 3434, "apartments": 3435, "acquiring": 3436, "necessities": 3437, "asha": 3438, "afterward": 3439, "picking": 3440, "b'best": 3441, "jumping": 3442, "staffs": 3443, "surely": 3444, "aways": 3445, "away'": 3446, "hardrock": 3447, "freuent": 3448, "booklet": 3449, "years'": 3450, "vents": 3451, "manage": 3452, "rumbled": 3453, "permanently": 3454, "background": 3455, "switched": 3456, "risk": 3457, "contributed": 3458, "brownies": 3459, "longer'": 3460, "makeover": 3461, "gaping": 3462, "mauled": 3463, "earthworm": 3464, "slumming": 3465, "props": 3466, "2703": 3467, "bumping": 3468, "grinding": 3469, "scheduled": 3470, "hrs": 3471, "comparing": 3472, "boutiques": 3473, "snooty'": 3474, "unpacking'": 3475, "dumpster": 3476, "filling": 3477, "emptying": 3478, "complainer'": 3479, "insist": 3480, "lamps": 3481, "mistakingly": 3482, "6pm'": 3483, "grandmother": 3484, "attic": 3485, "wall'": 3486, "elevators'": 3487, "ho": 3488, "ho'": 3489, "talbot'": 3490, "curtain": 3491, "noises": 3492, "app": 3493, "cranked": 3494, "puddle": 3495, "unbearably": 3496, "controls": 3497, "goodness": 3498, "we'd": 3499, "cooked": 3500, "alive": 3501, "thrown": 3502, "lock": 3503, "lively": 3504, "burn": 3505, "marks": 3506, "lead": 3507, "occupied": 3508, "tho": 3509, "prison": 3510, "cell": 3511, "raffel": 3512, "fund": 3513, "raiser": 3514, "united": 3515, "charity": 3516, "00am": 3517, "ways": 3518, "shouting": 3519, "profanities": 3520, "quieted": 3521, "exhausted": 3522, "managemnet": 3523, "certificate": 3524, "edges": 3525, "beat'": 3526, "ambulance": 3527, "sirens": 3528, "continued": 3529, "soundproofing": 3530, "rely": 3531, "cancelation": 3532, "suprise": 3533, "gusts": 3534, "basement": 3535, "stark": 3536, "led": 3537, "occasion'": 3538, "shambles": 3539, "literally": 3540, "uninformed'": 3541, "result": 3542, "seasoned": 3543, "yearly": 3544, "220": 3545, "decent'": 3546, "craptastic": 3547, "buttnaked": 3548, "head": 3549, "weak": 3550, "spray": 3551, "dribble": 3552, "cue": 3553, "david": 3554, "dancer": 3555, "'sup": 3556, "so'": 3557, "nightlife": 3558, "woken": 3559, "flooded'": 3560, "nw": 3561, "oir": 3562, "surgery": 3563, "insulation": 3564, "frames": 3565, "cars'": 3566, "thankful": 3567, "suppose": 3568, "redeeming": 3569, "generations": 3570, "jr": 3571, "furniture'": 3572, "ny'": 3573, "encouraged": 3574, "fortunate": 3575, "division": 3576, "upgrading": 3577, "usage": 3578, "shame": 3579, "missed": 3580, "thorugh": 3581, "websight": 3582, "drag": 3583, "attractiion": 3584, "overhauled": 3585, "projections": 3586, "finish": 3587, "circumstances": 3588, "lobbie": 3589, "unfinished": 3590, "drywall": 3591, "dean": 3592, "martin": 3593, "celebrity": 3594, "entertaining": 3595, "neighborhood'": 3596, "best'": 3597, "kiss": 3598, "makeup": 3599, "lighting": 3600, "linens'": 3601, "tile": 3602, "currently'": 3603, "loyal": 3604, "sad": 3605, "lodging": 3606, "deteriorates": 3607, "decades": 3608, "groupon": 3609, "treasures": 3610, "layed": 3611, "lifted": 3612, "distubing": 3613, "spotting": 3614, "8pm": 3615, "renamed": 3616, "dimly": 3617, "matters'": 3618, "110": 3619, "sites": 3620, "talbott'": 3621, "recall": 3622, "initially'": 3623, "scary": 3624, "scaffolding'": 3625, "caused": 3626, "smallest": 3627, "cta": 3628, "fourth": 3629, "overview": 3630, "45pm": 3631, "designers": 3632, "bagels": 3633, "healthy": 3634, "factor": 3635, "kinks": 3636, "basics": 3637, "stupid": 3638, "attempt": 3639, "ends": 3640, "skit": 3641, "functional": 3642, "shoe": 3643, "box": 3644, "pedestal": 3645, "sink": 3646, "closet": 3647, "pee": 3648, "costruction": 3649, "note'": 3650, "stately": 3651, "drawbacks": 3652, "interviewing": 3653, "position": 3654, "dated'": 3655, "airport'": 3656, "ridiculously": 3657, "stupid'": 3658, "analyst": 3659, "glance'": 3660, "confused": 3661, "levels": 3662, "excellently": 3663, "gm": 3664, "handling": 3665, "quoted": 3666, "125'": 3667, "sir": 3668, "madam": 3669, "feedback": 3670, "23": 3671, "operated": 3672, "vehicle": 3673, "glove": 3674, "compartments": 3675, "chagrin'": 3676, "repaired": 3677, "depite": 3678, "requests'": 3679, "attendant": 3680, "with'": 3681, "14th": 3682, "allegro'": 3683, "2010'": 3684, "owners": 3685, "flophouse'": 3686, "advised": 3687, "law": 3688, "bachelorette": 3689, "bottled": 3690, "giggling": 3691, "dance": 3692, "inattentive": 3693, "disrepair": 3694, "reported": 3695, "partially": 3696, "head'": 3697, "traditional": 3698, "lukewarm": 3699, "generator": 3700, "stool": 3701, "smear": 3702, "eeewwhh": 3703, "computer'": 3704, "b'in": 3705, "minneapolis": 3706, "miles": 3707, "desireable": 3708, "350": 3709, "imo": 3710, "justifying": 3711, "comments": 3712, "loading": 3713, "flors": 3714, "garbage": 3715, "530'": 3716, "b'how": 3717, "argue": 3718, "slide": 3719, "fills": 3720, "redickulas": 3721, "insure": 3722, "overcharging": 3723, "commonly": 3724, "reminded": 3725, "shining": 3726, "square": 3727, "exposed": 3728, "pipes'": 3729, "fridge": 3730, "wasvery": 3731, "review'": 3732, "unimpressed'": 3733, "fugitive": 3734, "furnitures'": 3735, "norway": 3736, "vacationing": 3737, "consequently": 3738, "'inner": 3739, "courtyard": 3740, "determine": 3741, "appliances": 3742, "ostentatious": 3743, "certaintly": 3744, "reserved'": 3745, "documents": 3746, "regards": 3747, "strawberries": 3748, "classified": 3749, "wouldn't": 3750, "consider": 3751, "jewish": 3752, "hindi": 3753, "appetizer": 3754, "entree": 3755, "portion": 3756, "meat": 3757, "forgettable": 3758, "dessert": 3759, "inedible": 3760, "extent": 3761, "influence": 3762, "tattered": 3763, "company'": 3764, "person'": 3765, "shula": 3766, "saff": 3767, "exteremely": 3768, "nonsmoking": 3769, "ancient": 3770, "tempermental'": 3771, "dump": 3772, "percentage": 3773, "outcomes": 3774, "younger": 3775, "smoker": 3776, "argued": 3777, "priority": 3778, "track": 3779, "eveing": 3780, "seal": 3781, "vendor": 3782, "unaccomodating": 3783, "insult": 3784, "injury": 3785, "obtained": 3786, "acceptable": 3787, "sightseeing'": 3788, "i'd": 3789, "exhaust": 3790, "upside'": 3791, "okay": 3792, "fifteen": 3793, "necessarily": 3794, "orchid": 3795, "bangkok'": 3796, "shock": 3797, "joke'": 3798, "grade": 3799, "cafeteria": 3800, "odors": 3801, "disgusting'": 3802, "swisses": 3803, "published": 3804, "distances": 3805, "chapter": 3806, "disagreement": 3807, "riverfront'": 3808, "billed": 3809, "750": 3810, "truely": 3811, "hideous": 3812, "experieince": 3813, "resort": 3814, "13'": 3815, "6th'": 3816, "parade": 3817, "speaking'": 3818, "bite'": 3819, "valentines": 3820, "sucks": 3821, "glasses": 3822, "notorious": 3823, "sensitive": 3824, "scales": 3825, "fridge'": 3826, "assure": 3827, "teens": 3828, "somehow": 3829, "sorted": 3830, "grungy'": 3831, "firtly": 3832, "372": 3833, "stood": 3834, "twenty": 3835, "aggravation": 3836, "grief'": 3837, "advice": 3838, "improve": 3839, "bailed": 3840, "stair": 3841, "wells": 3842, "breaker": 3843, "improved": 3844, "work'": 3845, "pipes": 3846, "obnoxious": 3847, "poisoning": 3848, "alert": 3849, "onsite": 3850, "painful": 3851, "torso": 3852, "bug": 3853, "itches": 3854, "wise'": 3855, "trading": 3856, "depressing": 3857, "classed": 3858, "neighbourhood'": 3859, "help'": 3860, "therefore": 3861, "basement'": 3862, "relocate": 3863, "address": 3864, "correct": 3865, "transfer": 3866, "keys": 3867, "selecting": 3868, "becaue": 3869, "concerned'": 3870, "'cold'": 3871, "faced": 3872, "trump": 3873, "action": 3874, "vacuuming": 3875, "00a": 3876, "verify": 3877, "imbarrassment": 3878, "hasnt": 3879, "2012": 3880, "corporation": 3881, "handicapped": 3882, "inexperienced": 3883, "similarly": 3884, "cheapest": 3885, "duing": 3886, "letting": 3887, "makeshift": 3888, "ache": 3889, "influx": 3890, "curt": 3891, "dishes": 3892, "dropping": 3893, "slower": 3894, "dial": 3895, "network": 3896, "overcharge": 3897, "bogus": 3898, "yahoo": 3899, "compressor": 3900, "postal": 3901, "correctly": 3902, "addressed": 3903, "transported": 3904, "ups": 3905, "denied": 3906, "ticket": 3907, "else'": 3908, "2sure": 3909, "eric'": 3910, "continues": 3911, "yawn": 3912, "state'": 3913, "tangled": 3914, "scratching": 3915, "skin": 3916, "crawling": 3917, "bedhead": 3918, "rice": 3919, "brown": 3920, "scurried": 3921, "insects": 3922, "cleaners": 3923, "fortunately": 3924, "protector": 3925, "hygeine": 3926, "rise": 3927, "door'": 3928, "couldin": 3929, "diffrerent": 3930, "fulfill": 3931, "losing": 3932, "worn'": 3933, "stinky": 3934, "mildew": 3935, "dubbed": 3936, "fawlty": 3937, "grease": 3938, "wafted": 3939, "greasy": 3940, "spoon": 3941, "permeated": 3942, "clothing": 3943, "shut'": 3944, "god": 3945, "moldy": 3946, "channels": 3947, "rerun": 3948, "58": 3949, "nonchalantly": 3950, "replied": 3951, "sink'": 3952, "alarm": 3953, "clock": 3954, "stereo": 3955, "emitting": 3956, "low'": 3957, "coupon": 3958, "file": 3959, "awaken": 3960, "cursing": 3961, "piddles": 3962, "passing": 3963, "them'": 3964, "maintain": 3965, "dublin'": 3966, "engineering": 3967, "sooner": 3968, "deceptively": 3969, "alters": 3970, "ie": 3971, "specialist": 3972, "72": 3973, "tremendously": 3974, "computerized": 3975, "backpack": 3976, "goodies": 3977, "otherwise'": 3978, "mints": 3979, "bedding'": 3980, "promise": 3981, "uncomfortably": 3982, "child": 3983, "managment": 3984, "bellhops": 3985, "visibly": 3986, "stressed": 3987, "flushed'": 3988, "subject": 3989, "inform": 3990, "reportedly": 3991, "9am": 3992, "slow'": 3993, "frustrating": 3994, "prominently": 3995, "acquaintances": 3996, "candidate": 3997, "recruiting": 3998, "meridien": 3999, "ryder": 4000, "comforter": 4001, "dirt": 4002, "handicap": 4003, "ironing": 4004, "board": 4005, "capacity": 4006, "stops": 4007, "ranks": 4008, "smoke'": 4009, "september'": 4010, "inherited": 4011, "result'": 4012, "surface": 4013, "gallery": 4014, "speak": 4015, "disrupt": 4016, "1500": 4017, "aspired": 4018, "slightest": 4019, "peep": 4020, "neighbor": 4021, "anyway": 4022, "choice'": 4023, "nye'": 4024, "dr": 4025, "27'": 4026, "infrastructure": 4027, "bridge": 4028, "towners": 4029, "tier": 4030, "marked": 4031, "row'": 4032, "annual": 4033, "decreased": 4034, "anyplace": 4035, "district'": 4036, "comparable": 4037, "olympia": 4038, "inspiring": 4039, "connection": 4040, "wire": 4041, "wire'": 4042, "impressing": 4043, "expressed": 4044, "adjacent": 4045, "40": 4046, "mistakes": 4047, "up'": 4048, "34th": 4049, "exact": 4050, "downgraded": 4051, "lesser": 4052, "moreover'": 4053, "clientele": 4054, "rambunctious": 4055, "seeming": 4056, "keeper": 4057, "bare": 4058, "minimum": 4059, "replace": 4060, "hurried": 4061, "blower": 4062, "blew": 4063, "freezing": 4064, "air'": 4065, "gloss": 4066, "nitghts": 4067, "upcoming": 4068, "paid'": 4069, "meaning": 4070, "congested": 4071, "tv'": 4072, "rug": 4073, "slippery": 4074, "throw": 4075, "ground": 4076, "minibar": 4077, "outmoded": 4078, "original": 4079, "produce": 4080, "drab": 4081, "downgrade": 4082, "joined": 4083, "overheard": 4084, "630": 4085, "sleepless": 4086, "facing": 4087, "mi": 4088, "sanjay": 4089, "mahajan": 4090, "light'": 4091, "defective": 4092, "engineers": 4093, "unit'": 4094, "badly": 4095, "stale": 4096, "belong": 4097, "league": 4098, "gucci": 4099, "sunglasses": 4100, "16th": 4101, "report": 4102, "anxious": 4103, "degree": 4104, "height": 4105, "futon": 4106, "canted": 4107, "configured": 4108, "depicted": 4109, "photos'": 4110, "pennisula'": 4111, "tons": 4112, "hawaii": 4113, "budapest": 4114, "adventist": 4115, "church": 4116, "drive'": 4117, "peace": 4118, "knowing": 4119, "laws": 4120, "prevent": 4121, "advising": 4122, "shoddy": 4123, "ceiling": 4124, "missing": 4125, "fist": 4126, "wires": 4127, "exposed'": 4128, "prime": 4129, "2day": 4130, "edit": 4131, "existing": 4132, "kings": 4133, "compensation": 4134, "rattled": 4135, "6pm": 4136, "squeezed": 4137, "singles": 4138, "blow": 4139, "pile": 4140, "unsatisfactory": 4141, "tremendous": 4142, "drawback": 4143, "survey": 4144, "triathlon": 4145, "piece": 4146, "afterwards": 4147, "vacuumed": 4148, "mopped": 4149, "5pm": 4150, "gotten": 4151, "yelp": 4152, "carlton": 4153, "prior'": 4154, "sufficient": 4155, "maker'": 4156, "3rd'": 4157, "new'": 4158, "74'": 4159, "decoration": 4160, "pressure": 4161, "reason'": 4162, "client": 4163, "answered": 4164, "inquiring": 4165, "'in": 4166, "reserve": 4167, "treadmill": 4168, "spanking": 4169, "99": 4170, "abound": 4171, "gripe": 4172, "highlight": 4173, "ceilings": 4174, "princess": 4175, "parlor": 4176, "retailer": 4177, "hide": 4178, "disturb": 4179, "un": 4180, "towel": 4181, "blanket'": 4182, "disliked": 4183, "blasted": 4184, "flight'": 4185, "valeted": 4186, "lexus": 4187, "smashed": 4188, "mirror": 4189, "admitted": 4190, "fault'": 4191, "news": 4192, "notably'": 4193, "layout'": 4194, "alleyways'": 4195, "dishonest'": 4196, "blowout": 4197, "stringers'": 4198, "rental": 4199, "matthews": 4200, "caravan": 4201, "tour": 4202, "outdoor": 4203, "200'": 4204, "adults": 4205, "kids'": 4206, "asleep": 4207, "chatting": 4208, "gossiping": 4209, "unprofessional": 4210, "'high'": 4211, "ha": 4212, "sill": 4213, "btw": 4214, "they've": 4215, "item": 4216, "retrospect'": 4217, "unhelpful'": 4218, "extremly": 4219, "promoting": 4220, "employee": 4221, "sexual": 4222, "advances": 4223, "talked": 4224, "blindfolded": 4225, "sworn": 4226, "hype": 4227, "loud'": 4228, "hello'": 4229, "unusable": 4230, "penetrate": 4231, "ease": 4232, "steep": 4233, "bust": 4234, "appearance": 4235, "dreary": 4236, "exterior": 4237, "desperate": 4238, "earned": 4239, "rushed": 4240, "notied": 4241, "lakeshore": 4242, "indicate": 4243, "aunt": 4244, "funeral": 4245, "recommedations": 4246, "dark'": 4247, "corporations": 4248, "represent": 4249, "revenue": 4250, "affinia'": 4251, "be'": 4252, "boats": 4253, "disclose": 4254, "tends": 4255, "heavily": 4256, "influenced": 4257, "wealth": 4258, "patrons'": 4259, "primarily": 4260, "unresponsive": 4261, "drunken": 4262, "teenagers": 4263, "ding'": 4264, "unaccommodating": 4265, "error": 4266, "abassador": 4267, "sw": 4268, "airshow": 4269, "permit": 4270, "beaches": 4271, "stick": 4272, "besides": 4273, "whirl": 4274, "usually'": 4275, "promises": 4276, "daughter's": 4277, "loves": 4278, "eight": 4279, "counted": 4280, "lifetime": 4281, "carriage": 4282, "canceled": 4283, "sulked": 4284, "cried": 4285, "herself": 4286, "fancy'": 4287, "tip'": 4288, "neo": 4289, "stylings": 4290, "force": 4291, "throat": 4292, "attacks": 4293, "pocket": 4294, "touts": 4295, "threadbare": 4296, "random": 4297, "checks'": 4298, "sort": 4299, "establishment'": 4300, "snubbed": 4301, "classier": 4302, "fancier": 4303, "budget'": 4304, "studio": 4305, "miserable": 4306, "code": 4307, "scrap": 4308, "delivered'": 4309, "sub": 4310, "guy's": 4311, "amateur": 4312, "accomidations": 4313, "mom'": 4314, "trigger": 4315, "hip": 4316, "rockers": 4317, "musicians": 4318, "hob": 4319, "kitchy": 4320, "affnia": 4321, "700": 4322, "unappetizing": 4323, "opening": 4324, "doors'": 4325, "details": 4326, "hairballs": 4327, "250": 4328, "dollars'": 4329, "4pm": 4330, "portray'": 4331, "frustratingly": 4332, "navigating": 4333, "arose": 4334, "arrange": 4335, "van": 4336, "finagling": 4337, "echilon": 4338, "hitched": 4339, "innovative": 4340, "emergency": 4341, "tonight": 4342, "300": 4343, "wasted": 4344, "ambience": 4345, "bland": 4346, "b'upon": 4347, "nose": 4348, "placing": 4349, "apologetically": 4350, "angry": 4351, "knocked": 4352, "irritated": 4353, "dealing": 4354, "angrily": 4355, "stormed": 4356, "smoother": 4357, "signals": 4358, "compare": 4359, "buttons": 4360, "slowly": 4361, "colder": 4362, "vise": 4363, "versa": 4364, "retire": 4365, "egyptian": 4366, "rent": 4367, "filthiest": 4368, "section": 4369, "starting": 4370, "179": 4371, "manager'": 4372, "outraged": 4373, "national": 4374, "association": 4375, "tade": 4376, "settle": 4377, "snarled": 4378, "beast": 4379, "aggressive": 4380, "snide": 4381, "comment": 4382, "mysteriously": 4383, "seeking": 4384, "brenda": 4385, "huffed": 4386, "puffed": 4387, "stepping": 4388, "propety": 4389, "functioning": 4390, "overpowering": 4391, "fragrance": 4392, "sinuses": 4393, "act": 4394, "wondered": 4395, "lug": 4396, "dragging": 4397, "lose": 4398, "contained": 4399, "valuable": 4400, "irreplaceable": 4401, "predicament": 4402, "evidence": 4403, "occupants": 4404, "conclude": 4405, "decorating'": 4406, "international": 4407, "shrouded": 4408, "glamour'": 4409, "cattle": 4410, "highlights": 4411, "teller": 4412, "forever'": 4413, "sept": 4414, "18'": 4415, "begins": 4416, "'warm": 4417, "greeting'": 4418, "struggling": 4419, "deceiving": 4420, "site'": 4421, "portray": 4422, "reputation": 4423, "wowed": 4424, "unmade": 4425, "supplies": 4426, "envisioned": 4427, "controlled'": 4428, "towncar": 4429, "assisting": 4430, "dropped": 4431, "pushed": 4432, "raised": 4433, "recieved": 4434, "wern't": 4435, "anymore": 4436, "yelling": 4437, "housekeeper": 4438, "energy": 4439, "retaurant": 4440, "seated": 4441, "former": 4442, "chicagoan'": 4443, "21st": 4444, "outside'": 4445, "dizzying": 4446, "bold": 4447, "patterns": 4448, "smells": 4449, "underwhelmed": 4450, "renovating": 4451, "definite": 4452, "everybody": 4453, "facilities": 4454, "job'": 4455, "dingy'": 4456, "suitcase'": 4457, "cover": 4458, "shocking": 4459, "flair": 4460, "guess'": 4461, "allego": 4462, "5'": 4463, "prolems": 4464, "subpar": 4465, "trainee": 4466, "priorities": 4467, "cigarettes": 4468, "frankly": 4469, "disgusting": 4470, "marred": 4471, "level'": 4472, "joke": 4473, "rack": 4474, "brochures": 4475, "leaning": 4476, "displeased": 4477, "beck": 4478, "call'": 4479, "guarantee": 4480, "eternity": 4481, "baskets": 4482, "row": 4483, "keepers": 4484, "safe'": 4485, "brand'": 4486, "made'": 4487, "dank": 4488, "awkward": 4489, "customers'": 4490, "fowl": 4491, "snooping": 4492, "albeit": 4493, "dimwitted": 4494, "did'": 4495, "inquire": 4496, "fond": 4497, "memories": 4498, "walk'": 4499, "superhigh": 4500, "automatically": 4501, "brochure": 4502, "intrigued": 4503, "wee": 4504, "college'": 4505, "swissotels": 4506, "much'": 4507, "getaway'": 4508, "disorganized": 4509, "key'": 4510, "ideas": 4511, "fine'": 4512, "gotta": 4513, "regarding'": 4514, "passable": 4515, "paying'": 4516, "'millennium": 4517, "boy'": 4518, "pricy'": 4519, "towers'": 4520, "story": 4521, "californians": 4522, "students": 4523, "university": 4524, "musky": 4525, "vomit'": 4526, "experiences'": 4527, "contemplated": 4528, "experienc": 4529, "document": 4530, "plush'": 4531, "hot'": 4532, "sheraton'": 4533, "paradise'": 4534, "belief": 4535, "farthest": 4536, "notice'": 4537, "shiny": 4538, "co": 4539, "upset": 4540, "persons": 4541, "wishing": 4542, "encounter": 4543, "duties": 4544, "conducted": 4545, "interactions": 4546, "diappointed": 4547, "substandarded": 4548, "hope": 4549, "resolved": 4550, "immensely": 4551, "produced": 4552, "copy": 4553, "arguing": 4554, "searched": 4555, "database": 4556, "claim": 4557, "extraordinary": 4558, "buy": 4559, "goto": 4560, "complemenatry": 4561, "overwhelming": 4562, "freshner": 4563, "x": 4564, "neighboring": 4565, "complain'": 4566, "highlighted": 4567, "discovered": 4568, "unfolding": 4569, "fifteenth": 4570, "tout": 4571, "glitch": 4572, "hung": 4573, "charges'": 4574, "goodness'": 4575, "sights'": 4576, "saved": 4577, "getway": 4578, "excitement": 4579, "frustrations": 4580, "impatient": 4581, "papers": 4582, "accomondations": 4583, "discussion": 4584, "unfortunatley'": 4585, "drips": 4586, "accepting": 4587, "responsibility'": 4588, "words'": 4589, "gouge": 4590, "fabulously": 4591, "decadent": 4592, "territory": 4593, "view'": 4594, "dissapointed": 4595, "convinced": 4596, "western": 4597, "centers": 4598, "cleaned'": 4599, "pregnant": 4600, "refused": 4601, "designs": 4602, "distraction": 4603, "snobby": 4604, "jobs": 4605, "old'": 4606, "chacago": 4607, "closest": 4608, "horrid": 4609, "irritable": 4610, "uncooperative": 4611, "uninviting": 4612, "rocks": 4613, "dreadful": 4614, "tastes": 4615, "vomit": 4616, "illicit": 4617, "pure": 4618, "500": 4619, "haphazardly": 4620, "ole": 4621, "word'": 4622, "michelin": 4623, "millemmium": 4624, "chagrin": 4625, "midnight": 4626, "reaked": 4627, "sightseeing": 4628, "over'": 4629, "pretty'": 4630, "latest": 4631, "oversold": 4632, "accepted": 4633, "commitments": 4634, "patiently": 4635, "tender": 4636, "horrified": 4637, "mysterious": 4638, "muttered": 4639, "changing": 4640, "beverage": 4641, "involved": 4642, "95": 4643, "begining": 4644, "inconveniece": 4645, "sheet": 4646, "misspelling": 4647, "although'": 4648, "displeasure": 4649, "websites'": 4650, "delays": 4651, "mutual": 4652, "glance": 4653, "creative": 4654, "photography": 4655, "westerns": 4656, "cleaner": 4657, "conditions": 4658, "age": 4659, "shows'": 4660, "drunks": 4661, "stumbling": 4662, "defiantly": 4663, "apparent": 4664, "photographs": 4665, "hadn't": 4666, "dusted": 4667, "online'": 4668, "lured": 4669, "showing": 4670, "ignored": 4671, "interrupted": 4672, "attitude": 4673, "sprayed": 4674, "febreeze": 4675, "scurry": 4676, "bedbugs": 4677, "whilst": 4678, "notably": 4679, "cleanliness'": 4680, "'hyatt": 4681, "ruined": 4682, "advertise": 4683, "entering'": 4684, "rudeness": 4685, "snubery": 4686, "booked'": 4687, "bills": 4688, "b'while": 4689, "chestnut": 4690, "advertisements": 4691, "dreamy": 4692, "dawn": 4693, "unaware": 4694, "disregarded": 4695, "bothersome": 4696, "swayed": 4697, "bringing": 4698, "tower'": 4699, "ready'": 4700, "hike": 4701, "cash": 4702, "feature": 4703, "fins": 4704, "attacked": 4705, "barking": 4706, "believing": 4707, "lure": 4708, "moncaco": 4709, "upstiff'": 4710, "watertower": 4711, "twice'": 4712, "assignment": 4713, "agreeable": 4714, "workable": 4715, "right'": 4716, "carrying": 4717, "till": 4718, "personality'": 4719, "b'eww": 4720, "sickening": 4721, "affair": 4722, "masterpiece": 4723, "reek": 4724, "pretended": 4725, "elite": 4726, "classes": 4727, "fill": 4728, "lie": 4729, "fear": 4730, "outrageous": 4731, "limits": 4732, "ultimately": 4733, "cash'": 4734, "creating": 4735, "nightclubs": 4736, "diamonds": 4737, "aaa'": 4738, "flipped": 4739, "switch": 4740, "collected": 4741, "determined": 4742, "disconnected": 4743, "ikea": 4744, "imediatly": 4745, "lasy": 4746, "tacky": 4747, "clashing": 4748, "rewards": 4749, "softiel": 4750, "dissatisfaction": 4751, "expense": 4752, "grandchildren": 4753, "deployed": 4754, "iraq": 4755, "mark": 4756, "stuffy'": 4757, "b'do": 4758, "pictured": 4759, "disheveled": 4760, "musty": 4761, "duration": 4762, "schicago": 4763, "record": 4764, "inappropriate": 4765, "arguing'": 4766, "greatly": 4767, "quit": 4768, "conversation": 4769, "trust": 4770, "baggage": 4771, "walmart": 4772, "'4": 4773, "strict": 4774, "gluten": 4775, "diet": 4776, "accomodate": 4777, "meal'": 4778, "greats": 4779, "cliche": 4780, "inspection'": 4781, "elected": 4782, "artistic'": 4783, "sending": 4784, "dressed": 4785, "impress'": 4786}